pyMSFT/__init__.py
pyMSFT/utilities.py
pyMSFT/shapes/__init__.py
pyMSFT/shapes/ellipsoid.py
pyMSFT/shapes/pointclouds.py
pyMSFT/shapes/shapes.py
pyMSFT/shapes/sphericalharmonics.py
pyMSFT/shapes/spindle.py
pyMSFT/shapes/voxel_to_mesh.py
pyMSFT/simulation/__init__.py
pyMSFT/simulation/mie_solutions.py
pyMSFT/simulation/simulation.py
pymsft-1.0.2.dist-info/licenses/LICENSE
pymsft-1.0.2.dist-info/METADATA
pymsft-1.0.2.dist-info/WHEEL
pymsft-1.0.2.dist-info/top_level.txt
pymsft-1.0.2.dist-info/RECORD
