Metadata-Version: 2.4
Name: pyMSFT
Version: 1.0.2
Summary: python MultiSlice Fourier-Transform toolbox
Author-email: Paul Tuemmler <paul.tuemmler@uni-rostock.de>, Christian Peltz <christian.peltz@uni-rostock.de>
License: CC-BY-4.0
Project-URL: Homepage, https://gitlab.uni-rostock.de/snp/pymsft
Classifier: Programming Language :: Python :: 3
Classifier: Operating System :: OS Independent
Classifier: Development Status :: 4 - Beta
Classifier: Environment :: GPU :: NVIDIA CUDA
Classifier: Intended Audience :: Science/Research
Classifier: Topic :: Scientific/Engineering :: Physics
Requires-Python: >=3.12
License-File: LICENSE
Requires-Dist: numpy~=2.3.2
Requires-Dist: pyfftw~=0.15.0
Requires-Dist: tqdm~=4.67.1
Requires-Dist: scipy~=1.16.1
Requires-Dist: pillow~=11.3.0
Provides-Extra: mie
Requires-Dist: scattnlay~=2.4; extra == "mie"
Dynamic: license-file
